<?xml version="1.0" encoding="utf-8"?>
<?xml-stylesheet type="text/xsl" href="/schemas/mrd-1.5.xsl"?>
<MRData xmlns="http://ergast.com/mrd/1.5" series="f1" url="http://ergast.com/api/f1/2022/6/laps/40" limit="30" offset="0" total="18">
	<RaceTable season="2022" round="6" lap="40">
		<Race season="2022" round="6" url="http://en.wikipedia.org/wiki/2022_Spanish_Grand_Prix">
			<RaceName>Spanish Grand Prix</RaceName>
			<Circuit circuitId="catalunya" url="http://en.wikipedia.org/wiki/Circuit_de_Barcelona-Catalunya">
				<CircuitName>Circuit de Barcelona-Catalunya</CircuitName>
				<Location lat="41.57" long="2.26111">
					<Locality>Montmeló</Locality>
					<Country>Spain</Country>
				</Location>
			</Circuit>
			<Date>2022-05-22</Date>
			<Time>13:00:00Z</Time>
			<LapsList>
				<Lap number="40">
					<Timing driverId="max_verstappen" lap="40" position="1" time="1:26.930"/>
					<Timing driverId="perez" lap="40" position="2" time="1:26.900"/>
					<Timing driverId="russell" lap="40" position="3" time="1:27.943"/>
					<Timing driverId="bottas" lap="40" position="4" time="1:27.449"/>
					<Timing driverId="sainz" lap="40" position="5" time="1:27.633"/>
					<Timing driverId="hamilton" lap="40" position="6" time="1:27.340"/>
					<Timing driverId="ocon" lap="40" position="7" time="1:27.301"/>
					<Timing driverId="norris" lap="40" position="8" time="1:27.280"/>
					<Timing driverId="vettel" lap="40" position="9" time="1:29.423"/>
					<Timing driverId="alonso" lap="40" position="10" time="1:28.445"/>
					<Timing driverId="tsunoda" lap="40" position="11" time="1:28.531"/>
					<Timing driverId="mick_schumacher" lap="40" position="12" time="1:29.501"/>
					<Timing driverId="ricciardo" lap="40" position="13" time="1:28.871"/>
					<Timing driverId="gasly" lap="40" position="14" time="1:28.617"/>
					<Timing driverId="stroll" lap="40" position="15" time="1:29.108"/>
					<Timing driverId="latifi" lap="40" position="16" time="1:30.826"/>
					<Timing driverId="kevin_magnussen" lap="40" position="17" time="1:28.467"/>
					<Timing driverId="albon" lap="40" position="18" time="1:33.007"/>
				</Lap>
			</LapsList>
		</Race>
	</RaceTable>
</MRData>
